agent_assembly_line/__init__.py
agent_assembly_line/agent.py
agent_assembly_line/agent_manager.py
agent_assembly_line/config.py
agent_assembly_line/exceptions.py
agent_assembly_line/llm_factory.py
agent_assembly_line/memory_assistant.py
agent_assembly_line/rest.py
agent_assembly_line/agents/aethelland-demo/README.md
agent_assembly_line/agents/aethelland-demo/aethelland-information.txt
agent_assembly_line/agents/aethelland-demo/config.yaml
agent_assembly_line/agents/aethelland-demo/rag_template.txt
agent_assembly_line/agents/chat-demo/config.yaml
agent_assembly_line/agents/chat-demo/example.txt
agent_assembly_line/agents/chat-demo/rag_template.txt
agent_assembly_line/data_loaders/__init__.py
agent_assembly_line/data_loaders/base_loader.py
agent_assembly_line/data_loaders/data_loader_factory.py
agent_assembly_line/data_loaders/diff_loader.py
agent_assembly_line/data_loaders/json_loader.py
agent_assembly_line/data_loaders/pdf_loader.py
agent_assembly_line/data_loaders/rest_api_loader.py
agent_assembly_line/data_loaders/rss_feed_loader.py
agent_assembly_line/data_loaders/text_loader.py
agent_assembly_line/data_loaders/web_loader.py
agent_assembly_line/data_loaders/xml_remote_loader.py
agent_assembly_line/micros/__init__.py
agent_assembly_line/micros/choose_agent_agent.py
agent_assembly_line/micros/clarity_agent.py
agent_assembly_line/micros/diff_details_agent.py
agent_assembly_line/micros/diff_sum_agent.py
agent_assembly_line/micros/fmi_weather_agent.py
agent_assembly_line/micros/intent_agent.py
agent_assembly_line/micros/one_word_agent.py
agent_assembly_line/micros/sentiment_agent.py
agent_assembly_line/micros/sum_agent.py
agent_assembly_line/micros/test_validator_agent.py
agent_assembly_line/micros/website_summary_agent.py
agent_assembly_line/micros/yes_no_agent.py
agent_assembly_line/middleware/base_dict_parser.py
agent_assembly_line/middleware/fmi_forecast_parser.py
agent_assembly_line/middleware/semantic_test_case.py
agent_assembly_line/models/document.py
agent_assembly_line-0.0.1.dist-info/licenses/LICENSE
agent_assembly_line-0.0.1.dist-info/METADATA
agent_assembly_line-0.0.1.dist-info/WHEEL
agent_assembly_line-0.0.1.dist-info/top_level.txt
agent_assembly_line-0.0.1.dist-info/RECORD
