Metadata-Version: 2.4
Name: agent-assembly-line
Version: 0.0.1
Summary: A package for building AI agents that can be easily embedded into existing software stacks.
Author: Thomas
License:                                  Apache License
Project-URL: Homepage, https://github.com/tm243/agent-assembly-line
Requires-Python: <3.14,>=3.9
License-File: LICENSE
Requires-Dist: openai
Requires-Dist: PyYAML
Requires-Dist: requests
Requires-Dist: langchain
Requires-Dist: langchain_community
Requires-Dist: langchain_chroma
Requires-Dist: langchain_ollama
Requires-Dist: langchain_openai
Requires-Dist: pandas
Requires-Dist: numpy<1.27.0,>=1.21.0; python_version < "3.13"
Requires-Dist: numpy>=1.26.0; python_version >= "3.13"
Requires-Dist: pytest
Requires-Dist: sqlalchemy
Requires-Dist: pip
Requires-Dist: tomli; python_version < "3.11"
Requires-Dist: unidiff
Requires-Dist: bs4
Requires-Dist: selenium
Requires-Dist: webdriver_manager
Requires-Dist: xmltodict
Requires-Dist: jq
Requires-Dist: aiounittest
Requires-Dist: newspaper3k
Requires-Dist: typing-inspect==0.9.0
Requires-Dist: lxml_html_clean
Requires-Dist: urllib3==1.26.20
Requires-Dist: python-multipart
Requires-Dist: pydantic==2.10.6
Requires-Dist: fastapi==0.115.8
Dynamic: license-file
